kavachnet/__init__.py
kavachnet/app.py
kavachnet/cli.py
kavachnet/vpn_checker.py
kavachnet/data/netify_vpn_asns.csv
kavachnet/data/vpn_ip_list.txt
kavachnet/data/vpn_sources.json
kavachnet-1.1.0.dist-info/licenses/LICENSE
kavachnet-1.1.0.dist-info/METADATA
kavachnet-1.1.0.dist-info/WHEEL
kavachnet-1.1.0.dist-info/entry_points.txt
kavachnet-1.1.0.dist-info/top_level.txt
kavachnet-1.1.0.dist-info/RECORD
