Metadata-Version: 2.4
Name: kavachnet
Version: 1.1.0
Summary: VPN & Proxy Detector
Project-URL: Homepage, https://github.com/RishabKr15/kavachnet
Project-URL: Bug Tracker, https://github.com/RishabKr15/kavachnet/issues
Requires-Python: >=3.11
License-File: LICENSE
Requires-Dist: streamlit
Requires-Dist: requests
Requires-Dist: pandas
Dynamic: license-file
